{
	"code":"N0000",
	"data":[
	   {
			"id":"1",
			"number":"201",
			"status":"2",					
			"seatCount":"三座",
			"time":"19-06-15 19:26",
			"showOrder":false,
			"artificer":{
				"name":"马小跳",
				"number":"204",
				"gender":"女",
				"tel":"133-3333-3333"
			},
			"guest":{						
				"feeTotal":"100.00"
			}
		},
		{
			"id":"2",
			"number":"202",
			"status":"1",					
			"seatCount":"三座",
			"time":"19-06-15 19:26",
			"showOrder":false,
			"artificer":{
				"name":"马小跳",
				"number":"204",
				"gender":"女",
				"tel":"133-3333-3333"
			},
			"guest":{						
				"feeTotal":"100.00"
			}
		},
		{
			"id":"3",
			"number":"203",
			"status":"3",					
			"seatCount":"三座",
			"time":"19-06-15 19:26",
			"showOrder":false,
			"artificer":{
				"name":"马小跳",
				"number":"204",
				"gender":"女",
				"tel":"133-3333-3333"
			},
			"guest":{						
				"feeTotal":"100.00"
			}
		},
		{
			"id":"4",
			"number":"204",
			"status":"4",					
			"seatCount":"三座",
			"time":"19-06-15 19:26",
			"showOrder":false,
			"artificer":{
				"name":"马小跳",
				"number":"204",
				"gender":"女",
				"tel":"133-3333-3333"
			},
			"guest":{						
				"feeTotal":"100.00"
			}
		},
		{
			"id":"5",
			"number":"205",
			"status":"2",					
			"seatCount":"三座",
			"time":"19-06-15 19:26",
			"showOrder":false,
			"artificer":{
				"name":"马小跳",
				"number":"204",
				"gender":"女",
				"tel":"133-3333-3333"
			},
			"guest":{						
				"feeTotal":"100.00"
			}
		}

	]
}